{"adult": false, "backdrop_path": null, "belongs_to_collection": null, "budget": 0, "genres": [{"id": 12, "name": "Adventure"}, {"id": 35, "name": "Comedy"}], "homepage": null, "id": 383356, "imdb_id": "tt2369914", "original_language": "en", "original_title": "The River", "overview": "On a sweltering hot day, a very pregnant Maria, desperate for a cooling swim, encounters obstacles on her path to the river.", "popularity": 0.656, "poster_path": "/qHI42k0iLLHSNKXbZGaBPqvTkTE.jpg", "production_companies": [], "production_countries": [], "release_date": "2013-04-05", "revenue": 0, "runtime": 12, "spoken_languages": [{"iso_639_1": "en", "name": "English"}], "status": "Released", "tagline": "", "title": "The River", "video": false, "vote_average": 8.5, "vote_count": 2, "_movieID": "383356", "_source": "themovedb", "created_utc_dt": "08/28/2019, 09:12:47"}