{"adult": false, "backdrop_path": "/v2Yrmppc4IaVSAzq9jvPoM3kVtt.jpg", "belongs_to_collection": null, "budget": 0, "genres": [{"id": 99, "name": "Documentary"}], "homepage": "http://www.thewhalemovie.com", "id": 77880, "imdb_id": "tt1708537", "original_language": "en", "original_title": "The Whale", "overview": "The true story of a young, wild killer whale - an orca - nicknamed Luna, who lost contact with his family on the coast of British Columbia and turned up alone in a narrow stretch of sea between mountains, a place called Nootka Sound.", "popularity": 1.238, "poster_path": "/kpzNLHeVLqdLNSSCYVXKPpWoOno.jpg", "production_companies": [{"id": 8059, "logo_path": null, "name": "Kinosmith", "origin_country": ""}, {"id": 8060, "logo_path": null, "name": "Mountainside Films", "origin_country": ""}], "production_countries": [{"iso_3166_1": "CA", "name": "Canada"}], "release_date": "2011-09-09", "revenue": 0, "runtime": 89, "spoken_languages": [{"iso_639_1": "en", "name": "English"}], "status": "Released", "tagline": "Friendship is bigger than we know.", "title": "The Whale", "video": false, "vote_average": 5.5, "vote_count": 11, "_movieID": "77880", "_source": "themovedb", "created_utc_dt": "08/28/2019, 10:30:22"}