{"adult": false, "backdrop_path": "/3KiBuEKLBAQSyBbWbYXiKK0RXDS.jpg", "belongs_to_collection": null, "budget": 0, "genres": [{"id": 35, "name": "Comedy"}, {"id": 80, "name": "Crime"}, {"id": 27, "name": "Horror"}, {"id": 53, "name": "Thriller"}], "homepage": null, "id": 244458, "imdb_id": "tt1567437", "original_language": "en", "original_title": "The Voices", "overview": "A mentally unhinged factory worker must decide whether to listen to his talking cat and become a killer, or follow his dog's advice to keep striving for normalcy.", "popularity": 6.755, "poster_path": "/lmnPpYkSFsuAxnO6WJhQOlVZCA0.jpg", "production_companies": [{"id": 8532, "logo_path": null, "name": "1984 Private Defense Contractors", "origin_country": ""}, {"id": 6667, "logo_path": null, "name": "Mandalay Vision", "origin_country": ""}, {"id": 264, "logo_path": "/fA90qwUKgPhMONqtwY60GaHRyrW.png", "name": "Studio Babelsberg", "origin_country": "DE"}], "production_countries": [{"iso_3166_1": "DE", "name": "Germany"}, {"iso_3166_1": "US", "name": "United States of America"}], "release_date": "2014-01-19", "revenue": 0, "runtime": 101, "spoken_languages": [{"iso_639_1": "en", "name": "English"}], "status": "Released", "tagline": "Hearing voices can be murder.", "title": "The Voices", "video": false, "vote_average": 6.3, "vote_count": 928, "_movieID": "244458", "_source": "themovedb", "created_utc_dt": "08/28/2019, 10:29:42"}