{"adult": false, "backdrop_path": "/u7ZiRakTdU2NeYIf0CdF1mr0P6D.jpg", "belongs_to_collection": null, "budget": 0, "genres": [{"id": 28, "name": "Action"}, {"id": 12, "name": "Adventure"}, {"id": 16, "name": "Animation"}, {"id": 27, "name": "Horror"}], "homepage": null, "id": 31967, "imdb_id": "tt1401113", "original_language": "en", "original_title": "Dante's Inferno: An Animated Epic", "overview": "Dante journeys through the nine circles of Hell -- limbo, lust, gluttony, greed, anger, heresy, violence, fraud and treachery -- in search of his true love, Beatrice. An animated version of the video game of the same name.", "popularity": 6.675, "poster_path": "/Acsy6i3nsUiZ8J3BGnEThHxlYPn.jpg", "production_companies": [{"id": 5385, "logo_path": null, "name": "Dong Woo Animation", "origin_country": ""}], "production_countries": [{"iso_3166_1": "US", "name": "United States of America"}, {"iso_3166_1": "JP", "name": "Japan"}, {"iso_3166_1": "SG", "name": "Singapore"}, {"iso_3166_1": "KR", "name": "South Korea"}], "release_date": "2010-02-09", "revenue": 0, "runtime": 84, "spoken_languages": [{"iso_639_1": "en", "name": "English"}, {"iso_639_1": "es", "name": "Espa\u00f1ol"}], "status": "Released", "tagline": "", "title": "Dante's Inferno: An Animated Epic", "video": false, "vote_average": 6.0, "vote_count": 107, "_movieID": "31967", "_source": "themovedb", "created_utc_dt": "08/28/2019, 09:26:28"}