{"adult": false, "backdrop_path": null, "belongs_to_collection": null, "budget": 0, "genres": [], "homepage": null, "id": 410672, "imdb_id": "tt2959530", "original_language": "en", "original_title": "Electric Cinema: How to Behave", "overview": "London's oldest working cinema asks its patrons to observe certain manners of behaviour when enjoying its shows.", "popularity": 1.4, "poster_path": "/nZ9keuVR1m64fEg5voeGVG5qUDb.jpg", "production_companies": [], "production_countries": [], "release_date": "2012-11-28", "revenue": 0, "runtime": 2, "spoken_languages": [{"iso_639_1": "en", "name": "English"}], "status": "Released", "tagline": "", "title": "Electric Cinema: How to Behave", "video": false, "vote_average": 5.7, "vote_count": 3, "_movieID": "410672", "_source": "themovedb", "created_utc_dt": "08/28/2019, 09:05:32"}