{"adult": false, "backdrop_path": null, "belongs_to_collection": null, "budget": 0, "genres": [], "homepage": null, "id": 330589, "imdb_id": "", "original_language": "en", "original_title": "WWE: The Rock vs John Cena: Once in a Lifetime", "overview": "A viewing experience through the return of The Rock to the WWE, and his feud with John Cena for Wrestlemania.", "popularity": 1.4, "poster_path": "/bI68ZoTPavaBGWc8XgYokDnHM7I.jpg", "production_companies": [{"id": 7588, "logo_path": "/jxduCllItpBzaBQU00mhD3bxjkE.png", "name": "World Wrestling Entertainment (WWE)", "origin_country": "US"}, {"id": 13651, "logo_path": "/rVJkMs9cSaE1BQoPiDcH6OxmaVZ.png", "name": "WWE Home Video", "origin_country": "US"}], "production_countries": [], "release_date": "2012-09-11", "revenue": 0, "runtime": 390, "spoken_languages": [], "status": "Released", "tagline": "", "title": "WWE: The Rock vs John Cena: Once in a Lifetime", "video": true, "vote_average": 6.0, "vote_count": 1, "_movieID": "330589", "_source": "themoviedb", "created_utc_dt": "09/14/2019, 14:00:03"}