{"adult": false, "backdrop_path": "/bbcuTz7rcypTEcsVsclpjjnCFEg.jpg", "belongs_to_collection": null, "budget": 8500000, "genres": [{"id": 18, "name": "Drama"}, {"id": 14, "name": "Fantasy"}, {"id": 878, "name": "Science Fiction"}], "homepage": "http://www.thezerotheorem-movie.com", "id": 157834, "imdb_id": "tt2333804", "original_language": "en", "original_title": "The Zero Theorem", "overview": "A computer hacker's goal to discover the reason for human existence continually finds his work interrupted thanks to the Management; this time, they send a teenager and lusty love interest to distract him.", "popularity": 8.409, "poster_path": "/jsaRDf5Syw0dueU0mSXh4r1yzs0.jpg", "production_companies": [{"id": 5125, "logo_path": "/t3oWTsVukmEzrZzvfr37XRBibo5.png", "name": "Le Pacte", "origin_country": "FR"}, {"id": 6716, "logo_path": null, "name": "Zanuck Independent", "origin_country": ""}, {"id": 11819, "logo_path": null, "name": "MediaPro Pictures", "origin_country": "RO"}, {"id": 16923, "logo_path": null, "name": "Zephyr Films", "origin_country": "GB"}, {"id": 27993, "logo_path": null, "name": "Picture Perfect Corporation", "origin_country": ""}, {"id": 27994, "logo_path": null, "name": "Wild Side Films", "origin_country": ""}, {"id": 6626, "logo_path": "/A1BnMoWjzjOrjzpWimyBQkf84mS.png", "name": "Voltage Pictures", "origin_country": "US"}], "production_countries": [{"iso_3166_1": "GB", "name": "United Kingdom"}, {"iso_3166_1": "FR", "name": "France"}, {"iso_3166_1": "US", "name": "United States of America"}, {"iso_3166_1": "RO", "name": "Romania"}], "release_date": "2013-09-20", "revenue": 770706, "runtime": 107, "spoken_languages": [{"iso_639_1": "en", "name": "English"}], "status": "Released", "tagline": "Nothing is Everything", "title": "The Zero Theorem", "video": false, "vote_average": 6.1, "vote_count": 641, "_movieID": "157834", "_source": "themoviedb", "created_utc_dt": "09/14/2019, 13:34:33"}